{"title":"Russian River Pinot Noir Tasting","description":"<p>Join us on <strong>Wednesday, April 16</strong>, from<strong> 4–7 PM</strong> at <strong>Whispering Vine South Creek</strong> for a focused tasting of <strong>Russian River Valley Pinot Noirs</strong>, showcasing the elegance, vibrancy, and complexity that define this world-renowned region.</p><p></p><p><strong>Tasting Fee: $35</strong> <em>(Buy a bottle from the tasting and your fee is refunded)</em></p><p></p><p><strong>Featured Wines:</strong></p><ul><li><strong>Bricoleur Pinot Noir 2021</strong> – <em>92 pts, Wine Enthusiast.</em> Complex and bright with cherry, hibiscus, pomegranate, and subtle five-spice notes.</li><li><strong>Belle Glos Dairyman Vineyard Pinot Noir 2021</strong> – <em>94 pts, Tasting Panel.</em> Luxurious and bold with spiced cranberry, black cherry, chocolate, and balsamic depth.</li><li><strong>EnRoute Les Pommiers Pinot Noir 2022</strong> – <em>93 pts, Wine Enthusiast. </em>Delicate and expressive with dried rose, cherry, and berry pie, supported by lively acidity and fine tannins.</li><li><strong>The Calling Russian River Pinot Noir 2022</strong> – <em>90 pts, Wine Enthusiast. </em>Floral and juicy with raspberry, cherry, orange blossom, and balanced acidity.</li></ul><p></p><p>Come explore the beauty and diversity of Russian River Pinot Noir—<strong>buy a bottle and your tasting is free.</strong></p>","location":"85 Foothill Rd Ste 1 Reno, NV 89511","startTime":"2025-04-16T23:00:00.000Z","endTime":"2025-04-17T02:00:00.000Z","id":"QzlPsQ","tock":false}